awslambdabootstrap/__init__.py
awslambdabootstrap/coordinator.py
awslambdabootstrap/logger.py
awslambdabootstrap-0.0.5.dist-info/LICENSE
awslambdabootstrap-0.0.5.dist-info/METADATA
awslambdabootstrap-0.0.5.dist-info/WHEEL
awslambdabootstrap-0.0.5.dist-info/top_level.txt
awslambdabootstrap-0.0.5.dist-info/RECORD
